README.md
setup.py
standalone.py
standalone.egg-info/PKG-INFO
standalone.egg-info/SOURCES.txt
standalone.egg-info/dependency_links.txt
standalone.egg-info/requires.txt
standalone.egg-info/top_level.txt